inc_join/__init__.py
inc_join/__version__.py
inc_join/inc_join.py
inc_join-0.1.3.dist-info/licenses/LICENSE
inc_join-0.1.3.dist-info/METADATA
inc_join-0.1.3.dist-info/WHEEL
inc_join-0.1.3.dist-info/top_level.txt
inc_join-0.1.3.dist-info/RECORD
