Metadata-Version: 2.4
Name: inc-join
Version: 0.1.3
Summary: This library implements an incremental join function to join 2 (usually large) incrementally refreshed tables, taking into account the refresh timestamp of each table and the fact that data might arrive late.
Author-email: Bas van den Berg <b.vdberg@c2h.nl>
License-Expression: LGPL-3.0-or-later
Project-URL: Homepage, https://github.com/basvdberg/IncrementalJoin
Project-URL: Repository, https://github.com/basvdberg/IncrementalJoin
Project-URL: Issues, https://github.com/basvdberg/IncrementalJoin/issues
Classifier: Programming Language :: Python :: 3
Classifier: Operating System :: OS Independent
Requires-Python: >=3.8
License-File: LICENSE
Requires-Dist: pyspark>=3.0.0
Dynamic: license-file
